[
  { "textName": "Roberto Dias da Silva" },
  { "icon": "description", "title": "Nome", "text": "Roberto Dias da Silva" },
  { "icon": "phone", "title": "Telefone", "text": "(51) 99999-9999" },
  { "icon": "mail", "title": "E-mail", "text": "drroberto@gmail.com" },
  {
    "icon": "home",
    "title": "Local",
    "text": "R. Mucio Teixeira, 1198, Menino Deus, Porto Alegre, RS"
  },
  {
    "icon": "store",
    "title": "Local",
    "text": "Av. Praia de Belas 1444, Menino Deus, Porto Alegre, RS"
  },
  {
    "icon": "summarize",
    "title": "Áreas",
    "list": ["Direito da familia", "Direito Trabalista", "Direito Criminal"]
  },
  { "icon": "pix", "title": "Chave pix", "text": "drroberto@gmail.com" },
  { "icon": "verified", "title": "Verificado", "text": "02 fev 2024" }
]
